LICENSE
decorator0/__init__.py
decorator0/py.typed
decorator0/util.py
python_decorator-0.0.2.2.dist-info/LICENSE
python_decorator-0.0.2.2.dist-info/METADATA
python_decorator-0.0.2.2.dist-info/WHEEL
python_decorator-0.0.2.2.dist-info/RECORD
