Metadata-Version: 2.1
Name: python-decorator
Version: 0.0.2.2
Summary: Python decorator.
Home-page: https://github.com/ChenyangGao/web-mount-packs/tree/main/python-module/python-decorator
License: MIT
Keywords: decorator
Author: ChenyangGao
Author-email: wosiwujm@gmail.com
Requires-Python: >=3.10,<4.0
Classifier: Development Status :: 5 - Production/Stable
Classifier: Intended Audience :: Developers
Classifier: License :: OSI Approved :: MIT License
Classifier: Operating System :: OS Independent
Classifier: Programming Language :: Python
Classifier: Programming Language :: Python :: 3
Classifier: Programming Language :: Python :: 3.10
Classifier: Programming Language :: Python :: 3.11
Classifier: Programming Language :: Python :: 3.12
Classifier: Programming Language :: Python :: 3 :: Only
Classifier: Topic :: Software Development
Classifier: Topic :: Software Development :: Libraries
Classifier: Topic :: Software Development :: Libraries :: Python Modules
Requires-Dist: python-partial (>=0.0.4,<0.0.5)
Requires-Dist: python-undefined
Project-URL: Repository, https://github.com/ChenyangGao/web-mount-packs/tree/main/python-module/python-decorator
